yaml_include/.gitignore
yaml_include/__init__.py
yaml_include/_version.py
yaml_include/constructor.py
yaml_include/data.py
yaml_include/funcs.py
yaml_include/py.typed
yaml_include/representer.py
pyyaml_include-2.2.dist-info/AUTHORS.md
pyyaml_include-2.2.dist-info/LICENSE
pyyaml_include-2.2.dist-info/METADATA
pyyaml_include-2.2.dist-info/WHEEL
pyyaml_include-2.2.dist-info/top_level.txt
pyyaml_include-2.2.dist-info/RECORD
