Metadata-Version: 2.1
Name: pyyaml-include
Version: 2.2
Summary: An extending constructor of PyYAML: include other YAML files into current YAML document
Author-email: liu xue yan <liu_xue_yan@foxmail.com>
License: GPLv3+
Project-URL: Homepage, https://github.com/tanbro/pyyaml-include
Project-URL: Repository, https://github.com/tanbro/pyyaml-include.git
Project-URL: Documentation, https://pyyaml-include.readthedocs.io/en/latest/
Project-URL: Issues, https://github.com/tanbro/pyyaml-include/issues
Project-URL: Changelog, https://github.com/tanbro/pyyaml-include/blob/main/CHANGELOG.md
Keywords: yaml,PyYAML,include,yml
Classifier: License :: OSI Approved :: GNU General Public License v3 or later (GPLv3+)
Classifier: Development Status :: 5 - Production/Stable
Classifier: Intended Audience :: Developers
Classifier: Programming Language :: Python
Classifier: Programming Language :: Python :: 3
Classifier: Programming Language :: Python :: 3 :: Only
Classifier: Programming Language :: Python :: 3.8
Classifier: Programming Language :: Python :: 3.9
Classifier: Programming Language :: Python :: 3.10
Classifier: Programming Language :: Python :: 3.11
Classifier: Programming Language :: Python :: 3.12
Classifier: Programming Language :: Python :: 3.13
Classifier: Programming Language :: Python :: Implementation :: CPython
Classifier: Programming Language :: Python :: Implementation :: PyPy
Classifier: Topic :: Software Development :: Libraries :: Python Modules
Classifier: Topic :: Text Processing :: Markup
Requires-Python: >=3.8
License-File: LICENSE
License-File: AUTHORS.md
Requires-Dist: PyYAML~=6.0
Requires-Dist: fsspec>=2021.04.0
Requires-Dist: typing-extensions; python_version < "3.11"
